ansible_vault_keys/__init__.py
ansible_vault_keys/cli.py
ansible_vault_keys/dotpath_utils.py
ansible_vault_keys/main.py
ansible_vault_keys/vault_utils.py
ansible_vault_keys/yaml_io.py
ansible_vault_keys-0.2.3.dist-info/licenses/LICENSE
ansible_vault_keys-0.2.3.dist-info/METADATA
ansible_vault_keys-0.2.3.dist-info/WHEEL
ansible_vault_keys-0.2.3.dist-info/entry_points.txt
ansible_vault_keys-0.2.3.dist-info/top_level.txt
ansible_vault_keys-0.2.3.dist-info/RECORD
