Metadata-Version: 2.4
Name: ansible-vault-keys
Version: 0.2.3
Summary: Selective encryption of YAML keys using Ansible Vault, with full round-trip support
Author-email: Joe DeKeyrel <joedekeyrel@email.com>
Keywords: ansible,vault,yaml,encryption,cli
Classifier: Development Status :: 3 - Alpha
Classifier: Intended Audience :: Developers
Classifier: License :: OSI Approved :: MIT License
Classifier: Programming Language :: Python :: 3
Classifier: Programming Language :: Python :: 3.8
Classifier: Programming Language :: Python :: 3.9
Classifier: Programming Language :: Python :: 3.10
Classifier: Programming Language :: Python :: 3.11
Classifier: Programming Language :: Python :: 3.12
Classifier: Programming Language :: Python :: 3.13
Classifier: Topic :: Utilities
Requires-Python: >=3.8
License-File: LICENSE
Requires-Dist: ansible>=2.18
Requires-Dist: ruamel.yaml>=0.18
Provides-Extra: dev
Requires-Dist: pytest; extra == "dev"
Requires-Dist: pytest-cov; extra == "dev"
Requires-Dist: coverage; extra == "dev"
Requires-Dist: ruff; extra == "dev"
Requires-Dist: build; extra == "dev"
Requires-Dist: twine; extra == "dev"
Requires-Dist: bumpver; extra == "dev"
Dynamic: license-file
